hirm/__init__.py
hirm/hirm.py
hirm/util_io.py
hirm/util_math.py
hirm/util_plot.py
hirm/tests/__init__.py
hirm/tests/test_basic.py
hirm/tests/util_test.py
hirm-0.1.3.dist-info/LICENSE.txt
hirm-0.1.3.dist-info/METADATA
hirm-0.1.3.dist-info/WHEEL
hirm-0.1.3.dist-info/top_level.txt
hirm-0.1.3.dist-info/RECORD
