Metadata-Version: 2.1
Name: hirm
Version: 0.1.3
Summary: Hierarchical Infinite Relational Model
Home-page: UNKNOWN
License: Apache-2.0
Platform: UNKNOWN
Classifier: Development Status :: 2 - Pre-Alpha
Classifier: Intended Audience :: Science/Research
Classifier: License :: OSI Approved :: Apache Software License
Requires-Python: >=3.6
Requires-Dist: matplotlib (==3.4.*)
Requires-Dist: numpy (==1.20.*)
Requires-Dist: pytest (==5.2.*)
Requires-Dist: scipy (==1.6.*)
Provides-Extra: all
Requires-Dist: matplotlib (==3.4.*) ; extra == 'all'
Requires-Dist: numpy (==1.20.*) ; extra == 'all'
Requires-Dist: pytest (==5.2.*) ; extra == 'all'
Requires-Dist: scipy (==1.6.*) ; extra == 'all'
Provides-Extra: examples
Requires-Dist: matplotlib (==3.4.*) ; extra == 'examples'
Requires-Dist: numpy (==1.20.*) ; extra == 'examples'
Provides-Extra: src
Requires-Dist: scipy (==1.6.*) ; extra == 'src'
Provides-Extra: tests
Requires-Dist: pytest (==5.2.*) ; extra == 'tests'
